HISTORY.rst
MANIFEST.in
README.rst
setup.cfg
setup.py
pythonanywhere_cli/__init__.py
pythonanywhere_cli/cli.py
pythonanywhere_cli/commands.py
pythonanywhere_cli/snakesay.py
tests/__init__.py
tests/__init__.pyc
tests/test_cli.py
tests/test_commands.py
tests/test_snakesay.py
tests/__pycache__/__init__.cpython-36.pyc
tests/__pycache__/test_cli.cpython-27-PYTEST.pyc
tests/__pycache__/test_cli.cpython-36-PYTEST.pyc
tests/__pycache__/test_commands.cpython-27-PYTEST.pyc
tests/__pycache__/test_commands.cpython-36-PYTEST.pyc
tests/__pycache__/test_snakesay.cpython-27-PYTEST.pyc
tests/__pycache__/test_snakesay.cpython-36-PYTEST.pyc