Metadata-Version: 1.1
Name: pythonanywhere_cli
Version: 0.3.0
Summary: PythonAnywhere Command Line Interface.
Home-page: https://github.com/cfc603/pythonanywhere-cli
Author: Trevor Watson
Author-email: wtrevor162@gmail.com
License: MIT
Keywords: pythonanywhere_cli cli pythonanywhere pythonanywhere-cli
Platform: UNKNOWN
Classifier: Intended Audience :: Developers
Classifier: Topic :: Utilities
Classifier: License :: OSI Approved :: MIT License
Classifier: Natural Language :: English
Classifier: Operating System :: OS Independent
Classifier: Programming Language :: Python :: 2
Classifier: Programming Language :: Python :: 2.7
Classifier: Programming Language :: Python :: 3
Classifier: Programming Language :: Python :: 3.2
Classifier: Programming Language :: Python :: 3.3
Classifier: Programming Language :: Python :: 3.4
Classifier: Programming Language :: Python :: 3.5
Classifier: Programming Language :: Python :: 3.6
Classifier: Topic :: Software Development :: Libraries :: Python Modules
